common/__init__.py
common/geid/__init__.py
common/geid/geid_client.py
common/jwt_handler/JWTHandler.py
common/jwt_handler/__init__.py
common/jwt_handler/jwt_handler_exception.py
common/jwt_handler/models.py
common/logging/__init__.py
common/logging/formatter.py
common/logging/logger.py
common/logging/logging.py
common/models/__init__.py
common/models/config_center_policy.py
common/models/service_id_generator.py
common/permissions/__init__.py
common/permissions/exceptions.py
common/permissions/permissions.py
common/permissions/permissions_manager.py
common/permissions/schemas.py
common/project/README.md
common/project/__init__.py
common/project/project_client.py
common/project/project_exceptions.py
common/services/__init__.py
common/services/auth_client.py
common/vault/__init__.py
common/vault/vault_client.py
common/vault/vault_exception.py
pilot_platform_common-2.14.0.dist-info/METADATA
pilot_platform_common-2.14.0.dist-info/WHEEL
pilot_platform_common-2.14.0.dist-info/RECORD
