Metadata-Version: 2.3
Name: pilot-platform-common
Version: 2.14.0
Summary: Common package used by various Pilot microservices.
Author: Indoc Systems
Author-email: support@indocsystems.com
Requires-Python: >=3.10,<3.13
Classifier: Operating System :: OS Independent
Classifier: Programming Language :: Python :: 3
Classifier: Programming Language :: Python :: 3.10
Classifier: Programming Language :: Python :: 3.11
Classifier: Programming Language :: Python :: 3.12
Requires-Dist: aioboto3 (>=14.3.0,<15.0.0)
Requires-Dist: cryptography (>=44.0.2,<45.0.0)
Requires-Dist: dicttoxml (>=1.7.16,<2.0.0)
Requires-Dist: httpx (>=0.28.1,<0.29.0)
Requires-Dist: opentelemetry-instrumentation-fastapi (>=0.53b1,<0.54)
Requires-Dist: opentelemetry-sdk (>=1.32.1,<2.0.0)
Requires-Dist: pydantic (>=2.7.1,<3.0.0)
Requires-Dist: pyjwt (>=2.10.1,<3.0.0)
Requires-Dist: python-dotenv (>=0.19.1)
Requires-Dist: python-json-logger (>=0.1.11,<=2.02)
Requires-Dist: redis (>=4.5.0,<7.0.0)
Requires-Dist: starlette (>=0.40.0,<0.47.0)
Requires-Dist: xmltodict (>=0.14.2,<0.15.0)
